.gitignore
LICENSE
README.md
requirements.txt
setup.py
bin/opencanary-correlator
opencanary_correlator/__init__.py
opencanary_correlator/dispatcher.py
opencanary_correlator/handlers.py
opencanary_correlator/opencanary_correlator.conf
opencanary_correlator/receiver.py
opencanary_correlator.egg-info/PKG-INFO
opencanary_correlator.egg-info/SOURCES.txt
opencanary_correlator.egg-info/dependency_links.txt
opencanary_correlator.egg-info/requires.txt
opencanary_correlator.egg-info/top_level.txt
opencanary_correlator/common/__init__.py
opencanary_correlator/common/config.py
opencanary_correlator/common/constants.py
opencanary_correlator/common/emailer.py
opencanary_correlator/common/incidents.py
opencanary_correlator/common/logs.py
opencanary_correlator/common/notifications.py
opencanary_correlator/common/queries.py
opencanary_correlator/common/redismanager.py
opencanary_correlator/common/utils.py