Metadata-Version: 1.0
Name: opencanary-correlator
Version: 0.1
Summary: opencanary correlator
Home-page: http://www.thinkst.com/
Author: Thinkst Applied Research
Author-email: info@thinkst.com
License: BSD
Platform: any
